tsrkit_types/__init__.py
tsrkit_types/bits.py
tsrkit_types/bool.py
tsrkit_types/bytearray.py
tsrkit_types/bytes.py
tsrkit_types/bytes_common.py
tsrkit_types/choice.py
tsrkit_types/dictionary.py
tsrkit_types/enum.py
tsrkit_types/integers.py
tsrkit_types/null.py
tsrkit_types/option.py
tsrkit_types/sequences.py
tsrkit_types/string.py
tsrkit_types/struct.py
tsrkit_types/itf/codable.py
tsrkit_types-0.1.9.dist-info/licenses/LICENSE
tsrkit_types-0.1.9.dist-info/METADATA
tsrkit_types-0.1.9.dist-info/WHEEL
tsrkit_types-0.1.9.dist-info/top_level.txt
tsrkit_types-0.1.9.dist-info/RECORD
