Metadata-Version: 2.4
Name: tsrkit-types
Version: 0.1.9
Summary: Performant Python Typings library for type-safe binary serialization, JSON encoding, and data validation with zero dependencies
Author-email: chainscore-labs <hello@chainscore.finance>, prasad-kumkar <prasad@chainscore.finance>
License-Expression: MIT
Project-URL: Homepage, https://github.com/chainscore/tsrkit-types
Project-URL: Repository, https://github.com/chainscore/tsrkit-types
Project-URL: Issues, https://github.com/chainscore/tsrkit-types/issues
Project-URL: Documentation, https://github.com/chainscore/tsrkit-types#readme
Project-URL: Changelog, https://github.com/chainscore/tsrkit-types/blob/main/CHANGELOG.md
Keywords: serialization,binary,encoding,types,codable,json,validation,data-types,type-safety,zero-copy,protocol,struct,networking,performance,bytes,integers,strings
Classifier: Development Status :: 4 - Beta
Classifier: Intended Audience :: Developers
Classifier: Intended Audience :: System Administrators
Classifier: Operating System :: OS Independent
Classifier: Programming Language :: Python :: 3
Classifier: Programming Language :: Python :: 3.11
Classifier: Programming Language :: Python :: 3.12
Classifier: Programming Language :: Python :: 3 :: Only
Classifier: Topic :: Software Development :: Libraries :: Python Modules
Classifier: Topic :: Software Development :: Libraries
Classifier: Topic :: System :: Networking
Classifier: Topic :: Internet :: WWW/HTTP
Classifier: Topic :: Database
Classifier: Topic :: Utilities
Classifier: Topic :: System :: Archiving
Classifier: Topic :: Communications
Classifier: Typing :: Typed
Requires-Python: <3.13,>=3.11
License-File: LICENSE
Provides-Extra: dev
Requires-Dist: pytest>=7.0.0; extra == "dev"
Requires-Dist: pytest-cov>=4.0.0; extra == "dev"
Requires-Dist: pytest-mock>=3.10.0; extra == "dev"
Requires-Dist: pytest-asyncio>=0.21.0; extra == "dev"
Requires-Dist: pytest-timeout>=2.1.0; extra == "dev"
Requires-Dist: pytest-xdist>=3.0.0; extra == "dev"
Dynamic: license-file
